articles/__init__.py
articles/admin.py
articles/bases.py
articles/content.py
articles/models.py
articles/search_indexes.py
articles/tests.py
articles/urls.py
articles/utils.py
articles/views.py
articles/extensions/__init__.py
articles/extensions/location.py
articles/extensions/tags.py
articles/extensions/thumbnail.py
articles/fixtures/articles_data.json
articles/fixtures/articles_datepublisher_data.json
articles/fixtures/articles_tags_data.json
articles/modules/__init__.py
articles/modules/category/__init__.py
articles/modules/category/admin.py
articles/modules/category/content.py
articles/modules/category/models.py
articles/modules/category/urls.py
articles/modules/category/views.py
articles/modules/category/extensions/__init__.py
articles/modules/category/extensions/category.py
articles/modules/category/templates/articles/categories.html
articles/modules/category/templates/articles/category_article_detail.html
articles/modules/category/templates/articles/category_article_list.html
articles/modules/category/templatetags/__init__.py
articles/modules/category/templatetags/articlecategory.py
articles/templates/articles/article_detail.html
articles/templates/articles/article_list.html
articles/templates/articles/articles.html
articles/templates/articles/base.html
articles/templates/content/articles/list.html
articles/templates/content/articles/category/default.html
articles/templates/search/indexes/articles/article_text.txt
articles/templatetags/__init__.py
articles/templatetags/article.py
feincms_articles-1.2.4.dist-info/LICENSE
feincms_articles-1.2.4.dist-info/METADATA
feincms_articles-1.2.4.dist-info/WHEEL
feincms_articles-1.2.4.dist-info/top_level.txt
feincms_articles-1.2.4.dist-info/RECORD
