Metadata-Version: 2.1
Name: feincms-articles
Version: 1.2.4
Summary: Provides Articles using (FeinCMS content) with categories and tags.
Home-page: https://github.com/incuna/feincms-articles/
Author: Incuna Ltd
Author-email: admin@incuna.com
License: BSD
Platform: UNKNOWN
Classifier: Development Status :: 5 - Production/Stable
Classifier: Environment :: Web Environment
Classifier: Framework :: Django
Classifier: Intended Audience :: Developers
Classifier: License :: OSI Approved :: BSD License
Classifier: Programming Language :: Python :: 2
Classifier: Programming Language :: Python :: 3
Classifier: Topic :: Internet :: WWW/HTTP :: Dynamic Content
Classifier: Topic :: Software Development
Classifier: Topic :: Software Development :: Libraries :: Application Frameworks
Requires-Dist: FeinCMS (>=1.7)
Requires-Dist: django-mptt
Requires-Dist: django-pagination
